InstructionFetchUnit.v
module InstructionFetchUnit (
    input wire pInPC,
    input wire pAluOut,
    input wire pInMemData,
    input wire pIorD,
    input wire pClk,
    input wire pDataValid,
    input wire pIRWrite,
    input wire pReset,
    output wire pAddr,
    output wire pOutInstr,
    output wire pOutData,
    output wire pOutPC,
    output wire pDataLoaded
);
    reg [31:0] pc;
    reg [31:0] addr;
    reg [31:0] outInstr;
    reg [31:0] outData;
    reg [31:0] outPC;
    reg dataLoaded;

    always @(posedge pClk or posedge pReset) begin
        if (pReset) begin
            addr <= 0;
            outInstr <= 0;
            outData <= 0;
        end else begin
            if (pIorD) begin
                pc <= pAluOut;
                addr <= pc;
            end else begin
                pc <= pInPC;
                addr <= pc;
            end
        end
        outPC <= pc + 32'h4;
    end

    always @(posedge pClk) begin
        if (pDataValid && pIRWrite) begin
            dataLoaded <= 1;
            outInstr <= pInMemData;
            outData <= 0;
        end else if (pDataValid && !pIRWrite) begin
            dataLoaded <= 1;
            outInstr <= 0;
            outData <= pInMemData;
        end else begin
            dataLoaded <= 0;
            outInstr <= 0;
            outData <= 0;
        end
    end

    assign pAddr = addr;
    assign pOutInstr = outInstr;
    assign pOutData = outData;
    assign pOutPC = outPC;
    assign pDataLoaded = dataLoaded;

endmodule

InstructionFetchUnit_TestBench.v
module InstructionFetchUnit_TestBench;
    reg pInPC;
    reg pAluOut;
    reg pInMemData;
    reg pIorD;
    reg pClk;
    reg pDataValid;
    reg pIRWrite;
    reg pReset;
    
    wire pAddr;
    wire pOutInstr;
    wire pOutData;
    wire pOutPC;
    wire pDataLoaded;
    
    InstructionFetchUnit DUT (
        .pInPC(pInPC),
        .pAluOut(pAluOut),
        .pInMemData(pInMemData),
        .pIorD(pIorD),
        .pClk(pClk),
        .pDataValid(pDataValid),
        .pIRWrite(pIRWrite),
        .pReset(pReset),
        .pAddr(pAddr),
        .pOutInstr(pOutInstr),
        .pOutData(pOutData),
        .pOutPC(pOutPC),
        .pDataLoaded(pDataLoaded)
    );
    
    initial begin
        $dumpfile("simulation.vcd");
        $dumpvars(0, InstructionFetchUnit_TestBench);

        pClk = 0;
        pReset = 1;
        #10 pReset = 0; // Deassert reset after 10 time units
        
        // Test Case 1: Fetch from Instruction Memory
        pInPC = 32'h1000;
        pAluOut = 0;
        pInMemData = 32'h12345678;
        pIorD = 0;
        pDataValid = 1;
        pIRWrite = 1;
        #20;
        
        // Test Case 2: Fetch from Data Memory
        pInPC = 32'h2000;
        pAluOut = 0;
        pInMemData = 32'h87654321;
        pIorD = 1;
        pDataValid = 1;
        pIRWrite = 0;
        #20;
        
        // Test Case 3: Fetch from ALU output
        pInPC = 32'h3000;
        pAluOut = 32'h4000;
        pInMemData = 0;
        pIorD = 1;
        pDataValid = 1;
        pIRWrite = 1;
        #20;
        
        // Run the simulation for additional time
        #100;
        
        $finish;
    end
    
    always #5 pClk = ~pClk;
    
    reg [6:0] sim_time = 0;
    integer sim_duration = 500; // Set the desired simulation duration here
    
    always @(posedge pClk) begin
        if (pDataLoaded && pIRWrite) begin
            $display("Output Instruction: %h", pOutInstr);
        end else if (pDataLoaded && !pIRWrite) begin
            $display("Output Data: %h", pOutData);
        end
        
        if (sim_time == sim_duration) begin
            $display("Simulation finished at time %d", sim_time);
            $finish;
        end
        sim_time = sim_time + 1;
    end
endmodule

simulation.vcd
$date
	Wed May 17 12:15:00 2023
$end
$version
	Icarus Verilog
$end
$timescale
	1s
$end
$scope module InstructionFetchUnit_TestBench $end
$var wire 1 ! pOutPC $end
$var wire 1 " pOutInstr $end
$var wire 1 # pOutData $end
$var wire 1 $ pDataLoaded $end
$var wire 1 % pAddr $end
$var reg 1 & pAluOut $end
$var reg 1 ' pClk $end
$var reg 1 ( pDataValid $end
$var reg 1 ) pIRWrite $end
$var reg 1 * pInMemData $end
$var reg 1 + pInPC $end
$var reg 1 , pIorD $end
$var reg 1 - pReset $end
$var reg 7 . sim_time [6:0] $end
$var integer 32 / sim_duration [31:0] $end
$scope module DUT $end
$var wire 1 & pAluOut $end
$var wire 1 ' pClk $end
$var wire 1 $ pDataLoaded $end
$var wire 1 ( pDataValid $end
$var wire 1 ) pIRWrite $end
$var wire 1 * pInMemData $end
$var wire 1 + pInPC $end
$var wire 1 , pIorD $end
$var wire 1 - pReset $end
$var wire 1 ! pOutPC $end
$var wire 1 " pOutInstr $end
$var wire 1 # pOutData $end
$var wire 1 % pAddr $end
$var reg 32 0 addr [31:0] $end
$var reg 1 1 dataLoaded $end
$var reg 32 2 outData [31:0] $end
$var reg 32 3 outInstr [31:0] $end
$var reg 32 4 outPC [31:0] $end
$var reg 32 5 pc [31:0] $end
$upscope $end
$upscope $end
$enddefinitions $end
#0
$dumpvars
bx 5
bx 4
b0 3
b0 2
x1
b0 0
b111110100 /
b0 .
1-
x,
x+
x*
x)
x(
0'
x&
0%
x$
0#
0"
x!
$end
#5
0$
01
b1 .
1'
#10
0'
1)
1(
0,
0*
0&
0+
0-
#15
x%
1$
11
bx 0
b0 5
b10 .
1'
#20
0'
#25
0!
0%
b100 4
b0 0
b11 .
1'
#30
0'
0)
1,
1*
#35
1#
b1 2
b100 .
1'
#40
0'
#45
b101 .
1'
#50
0'
1)
0*
#55
0#
b0 2
b110 .
1'
#60
0'
#65
b111 .
1'
#70
0'
#75
b1000 .
1'
#80
0'
#85
b1001 .
1'
#90
0'
#95
b1010 .
1'
#100
0'
#105
b1011 .
1'
#110
0'
#115
b1100 .
1'
#120
0'
#125
b1101 .
1'
#130
0'
#135
b1110 .
1'
#140
0'
#145
b1111 .
1'
#150
0'
#155
b10000 .
1'
#160
0'
#165
b10001 .
1'
